crudtoml/__init__.py
crudtoml/__main__.py
crudtoml-0.1.1.dist-info/entry_points.txt
crudtoml-0.1.1.dist-info/LICENSE
crudtoml-0.1.1.dist-info/WHEEL
crudtoml-0.1.1.dist-info/METADATA
crudtoml-0.1.1.dist-info/RECORD
