Metadata-Version: 2.1
Name: crudtoml
Version: 0.1.1
Summary: Perform CRUD operations on TOML files.
Keywords: TOML
Author-email: Edward Knight <edw@rdknig.ht>
Requires-Python: ~= 3.10
Classifier: Development Status :: 4 - Beta
Classifier: Environment :: Console
Classifier: Intended Audience :: Developers
Classifier: Intended Audience :: System Administrators
Classifier: License :: OSI Approved :: MIT License
Classifier: Natural Language :: English
Classifier: Programming Language :: Python :: 3
Classifier: Topic :: File Formats
Classifier: Topic :: Text Processing
Classifier: Topic :: Utilities
Classifier: Typing :: Typed
Requires-Dist: tomlkit ~= 0.8
Project-URL: Home, https://github.com/Edward-Knight/crudtoml
